ncn/__init__.py
ncn/nominal_composition_notation.py
ncn-0.0.5.dist-info/licenses/LICENSE
ncn-0.0.5.dist-info/METADATA
ncn-0.0.5.dist-info/WHEEL
ncn-0.0.5.dist-info/top_level.txt
ncn-0.0.5.dist-info/RECORD
