Metadata-Version: 2.4
Name: ncn
Version: 0.0.5
Summary: Use cnc to name, parse and find nominal composition notation.
Author-email: Hang Luo <haaaatcher@gmail.com>
License-Expression: Apache-2.0
Project-URL: Homepage, https://github.com/Haaaatcher
Keywords: nominal composition notation
Classifier: Programming Language :: Python :: 3
Classifier: Operating System :: OS Independent
Requires-Python: >=3.9
License-File: LICENSE
Requires-Dist: periodictable>=2.0.0
Dynamic: license-file
